Metadata-Version: 1.0
Name: litetable
Version: 0.1.1
Summary: LiteTable provides convenient data table objects for Python with SQL backend.
Home-page: https://github.com/jlintusaari/litetable
Author: Jarno Lintusaari
Author-email: jarno.lintusaari@gmail.com
License: BSD-3
Platform: UNKNOWN
